sphinxcontrib_fancybox-0.3.5-py2.7-nspkg.pth
sphinxcontrib_fancybox-0.3.5.dist-info/WHEEL
sphinxcontrib_fancybox-0.3.5.dist-info/metadata.json
sphinxcontrib_fancybox-0.3.5.dist-info/RECORD
sphinxcontrib_fancybox-0.3.5.dist-info/METADATA
sphinxcontrib_fancybox-0.3.5.dist-info/DESCRIPTION.rst
sphinxcontrib_fancybox-0.3.5.dist-info/top_level.txt
sphinxcontrib_fancybox-0.3.5.dist-info/namespace_packages.txt
sphinxcontrib/fancybox.py
sphinxcontrib/fancybox/fancybox_sprite.png
sphinxcontrib/fancybox/fancybox_loading@2x.gif
sphinxcontrib/fancybox/jquery.fancybox.css
sphinxcontrib/fancybox/jquery.fancybox.pack.js
sphinxcontrib/fancybox/fancybox_sprite@2x.png
sphinxcontrib/fancybox/fancybox_loading.gif
sphinxcontrib/fancybox/fancybox_overlay.png
sphinxcontrib/fancybox/blank.gif
