Metadata-Version: 2.0
Name: sphinxcontrib-fancybox
Version: 0.3.5
Summary: Sphinx "fancybox" extension
Home-page: http://spinus.github.com/sphinxcontrib-fancybox
Author: Tomek Czyż
Author-email: tomekczyz@gmail.com
License: BSD
Download-URL: http://pypi.python.org/pypi/sphinxcontrib-fancybox
Platform: any
Classifier: Development Status :: 4 - Beta
Classifier: Environment :: Console
Classifier: Environment :: Web Environment
Classifier: Intended Audience :: Developers
Classifier: License :: OSI Approved :: BSD License
Classifier: Operating System :: OS Independent
Classifier: Programming Language :: Python
Classifier: Topic :: Documentation
Requires-Dist: Sphinx (>=0.9)
